schwabkit/__init__.py
schwabkit/api.py
schwabkit/stream.py
schwabkit/terminal.py
schwabkit-0.0.6.dist-info/METADATA
schwabkit-0.0.6.dist-info/WHEEL
schwabkit-0.0.6.dist-info/top_level.txt
schwabkit-0.0.6.dist-info/RECORD
